adbauto/__init__.py
adbauto/adb.py
adbauto/input.py
adbauto/screen.py
adbauto/bin/AdbWinApi.dll
adbauto/bin/AdbWinUsbApi.dll
adbauto/bin/adb.exe
adbauto/scrcpy/__init__.py
adbauto/scrcpy/const.py
adbauto/scrcpy/control.py
adbauto/scrcpy/core.py
adbauto/scrcpy/scrcpy-server.jar
adbauto-1.0.9.dist-info/licenses/LICENSE
adbauto-1.0.9.dist-info/METADATA
adbauto-1.0.9.dist-info/WHEEL
adbauto-1.0.9.dist-info/top_level.txt
adbauto-1.0.9.dist-info/RECORD
