Metadata-Version: 2.4
Name: adbauto
Version: 1.0.9
Summary: A Python ADB automation library for Android emulators.
Author: Thoteman
License: MIT
Project-URL: Homepage, https://github.com/Thoteman/adbauto
Project-URL: Repository, https://github.com/Thoteman/adbauto
Requires-Python: >=3.8
License-File: LICENSE
Requires-Dist: opencv-python
Requires-Dist: numpy
Dynamic: license-file
